Workbook

Sheet 1. Instructions
C2: IT Department Budget Template Instructions
C4: The IT Department Budget Template is an Excel spreadsheet that can be used to develop your annual IT
C5: Department budget. There are four worksheet tabs:
C7: 1. Instructions
C8: Read the instructions on this first tab before using this template to develop your budget.
C10: 2. Monthly Worksheet
C11: This is the tab that you can use to enter the value for each of the budget line
C13: 3. Department Budget
C14: This is a summary of the budget : it will calculate automatically from the Monthly Worksheet
C18: Please note the following:
C19: Only input numbers into cells that have a blue font color

Sheet 2. Monthly Worksheet
A1: IT Department Budget | B1: Last Year's Budget | C1: Month 1 | D1: Month 2 | E1: Month 3 | F1: Month 4 | G1: Month 5 | H1: Month 6 | I1: Month 7 | J1: Month 8 | K1: Month 9 | L1: Month 10 | M1: Month 11 | N1: Month 12 | O1: TOTALS | P1: Comments/Assumptions
A2: Monthly Worksheet | B2: (Full Year) | C2: Jan | D2: Feb | E2: Mar | F2: Apr | G2: May | H2: Jun | I2: Jul | J2: Aug | K2: Sep | L2: Oct | M2: Nov | N2: Dec
A3: DEPARTMENT REVENUES
A4: Fees IT Charges for Services Performed | B4: =15000*12 -> 180000 | C4: $16,500 | D4: $16,500 | E4: $16,500 | F4: $16,500 | G4: $16,500 | H4: $16,500 | I4: $16,500 | J4: $16,500 | K4: $16,500 | L4: $16,500 | M4: $16,500 | N4: $16,500 | O4: 198000 | P4: 150$/Mth/Emp. Assumed 10% HC growth.
A5: Proceeds from Sales of Assets | B5: 20000 | C5: 0 | D5: 0 | E5: 0 | F5: 0 | G5: 0 | H5: 0 | I5: 0 | J5: 0 | K5: 0 | L5: 0 | M5: 0 | N5: 0 | O5: 0 | P5: Obsolete assets to be givent to schools.
A6: Other | O6: =SUM(C6:N6) -> 0
A7: Total Department Revenue | B7: =SUM(B4:B6) -> 200000 | C7: =SUM(C4:C6) -> 0 | D7: =SUM(D4:D6) -> 0 | E7: =SUM(E4:E6) -> 0 | F7: =SUM(F4:F6) -> 0 | G7: =SUM(G4:G6) -> 0 | H7: =SUM(H4:H6) -> 0 | I7: =SUM(I4:I6) -> 0 | ... N7: =SUM(N4:N6) -> 0 | O7: =SUM(C7:N7) -> 0
A9: PERSONNEL
A10: Headcount (People not Dollars)
A11: Full-Time | B11: 5 | C11: 6 | D11: 6 | E11: 6 | F11: 6 | G11: 6 | H11: 6 | I11: 6 | J11: 6 | K11: 6 | L11: 6 | M11: 6 | N11: 6
A12: Contract | B12: 3 | C12: 3 | D12: 3 | E12: 3 | F12: 3 | G12: 3 | H12: 8 | I12: 8 | J12: 8 | K12: 8 | L12: 8 | M12: 8 | N12: 3
A13: Other | C13: 0 | D13: 0 | E13: 1 | F13: 1 | G13: 1 | H13: 1 | I13: 1 | J13: 1 | K13: 1 | L13: 1 | M13: 1 | N13: 1
A14: Total Headcount | B14: =SUM(B11:B13) -> 8 | C14: =SUM(C11:C13) -> 9 | D14: =SUM(D11:D13) -> 9 | E14: =SUM(E11:E13) -> 10 | F14: =SUM(F11:F13) -> 10 | G14: =SUM(G11:G13) -> 10 | H14: =SUM(H11:H13) -> 15 | I14: =SUM(I11:I13) -> 15 | ... N14: =SUM(N11:N13) -> 10
A16: DEPARTMENT EXPENSES
A17: Personnel Expenses (Dollars not People)
A18: Full-Time Salaries | B18: 325000 | C18: =K10 -> 0 | D18: =D11*5400 -> 32400 | E18: =E11*5400 -> 32400 | F18: =F11*5400 -> 32400 | G18: =G11*5400 -> 32400 | H18: =H11*5400 -> 32400 | I18: =I11*5400 -> 32400 | J18: =J11*5400 -> 32400 | K18: =K11*5400 -> 32400 | ... N18: =N11*5400 -> 32400 | O18: =SUM(C18:N18) -> 356400
A19: Temporary Workers | O19: =SUM(C19:N19) -> 0
A20: Bonuses / Other Compensation | B20: 40000 | O20: =SUM(C20:N20) -> 0
A21: Employee Benefits | C21: =C11*120 -> 720 | D21: =D11*120 -> 720 | E21: =E11*120 -> 720 | F21: =F11*120 -> 720 | G21: =G11*120 -> 720 | H21: =H11*120 -> 720 | I21: =I11*120 -> 720 | J21: =J11*120 -> 720 | ... N21: =N11*120 -> 720 | O21: =SUM(C21:N21) -> 8640
A22: Consultants | C22: =C13*10000 -> 0 | D22: =D13*10000 -> 0 | E22: =E13*10000 -> 10000 | F22: =F13*10000 -> 10000 | G22: =G13*10000 -> 10000 | H22: =H13*10000 -> 10000 | I22: =I13*10000 -> 10000 | J22: =J13*10000 -> 10000 | ... N22: =N13*10000 -> 10000 | O22: =SUM(C22:N22) -> 100000
A23: Outsourcing Contracts | B23: 255000 | C23: =C12*85000/12 -> 21250 | D23: =D12*85000/12 -> 21250 | E23: =E12*85000/12 -> 21250 | F23: =F12*85000/12 -> 21250 | G23: =G12*85000/12 -> 21250 | H23: =H12*85000/12 -> 56666.667 | I23: =I12*85000/12 -> 56666.667 | J23: =J12*85000/12 -> 56666.667 | ... N23: =N12*85000/12 -> 21250 | O23: =SUM(C23:N23) -> 467500
A24: Training / Seminars | O24: =SUM(C24:N24) -> 0
A25: Automobile Expense | O25: =SUM(C25:N25) -> 0
A26: Travel (e.g. Plane Tickets) | O26: =SUM(C26:N26) -> 0
A27: Accomodation (e.g. Hotels) | O27: =SUM(C27:N27) -> 0
A28: Meals | O28: =SUM(C28:N28) -> 0
A29: Employee Relocation | O29: =SUM(C29:N29) -> 0
A30: Total Personnel Expenses | B30: =SUM(B18:B29) -> 620000 | C30: =SUM(C18:C29) -> 21970 | D30: =SUM(D18:D29) -> 54370 | E30: =SUM(E18:E29) -> 64370 | F30: =SUM(F18:F29) -> 64370 | G30: =SUM(G18:G29) -> 64370 | H30: =SUM(H18:H29) -> 99786.667 | I30: =SUM(I18:I29) -> 99786.667 | ... N30: =SUM(N18:N29) -> 64370 | O30: =SUM(C30:N30) -> 932540
A32: Office Supplies
A33: General Supplies | O33: =SUM(C33:N33) -> 0
A34: Media Costs (Diskettes, CDs, Tapes, etc.) | O34: =SUM(C34:N34) -> 0
A35: Postage / Freight | O35: =SUM(C35:N35) -> 0
A36: Publication Costs | O36: =SUM(C36:N36) -> 0
A37: Total Office Supplies | B37: =SUM(B33:B36) -> 0 | C37: =SUM(C33:C36) -> 0 | D37: =SUM(D33:D36) -> 0 | E37: =SUM(E33:E36) -> 0 | F37: =SUM(F33:F36) -> 0 | G37: =SUM(G33:G36) -> 0 | H37: =SUM(H33:H36) -> 0 | I37: =SUM(I33:I36) -> 0 | ... N37: =SUM(N33:N36) -> 0 | O37: =SUM(C37:N37) -> 0
A39: Telecommunications Expenses
A40: Local Telephone | O40: =SUM(C40:N40) -> 0
A41: Long Distance | O41: =SUM(C41:N41) -> 0
A42: Cellular | O42: =SUM(C42:N42) -> 0
A43: Pagers | O43: =SUM(C43:N43) -> 0
A44: Communications Lines | O44: =SUM(C44:N44) -> 0
A45: Internet Access | O45: =SUM(C45:N45) -> 0
A46: Other | O46: =SUM(C46:N46) -> 0
A47: Total Telecommunications Expenses | B47: =SUM(B40:B46) -> 0 | C47: =SUM(C40:C46) -> 0 | D47: =SUM(D40:D46) -> 0 | E47: =SUM(E40:E46) -> 0 | F47: =SUM(F40:F46) -> 0 | G47: =SUM(G40:G46) -> 0 | H47: =SUM(H40:H46) -> 0 | I47: =SUM(I40:I46) -> 0 | ... N47: =SUM(N40:N46) -> 0 | O47: =SUM(C47:N47) -> 0
A49: Equipment Costs - Capital (on Balance Sheet)
A50: Servers | O50: =SUM(C50:N50) -> 0
A51: Network Equipment | O51: =SUM(C51:N51) -> 0
A52: Other | O52: =SUM(C52:N52) -> 0
A53: Total Equipment Costs - Capital | B53: =SUM(B50:B52) -> 0 | C53: =SUM(C50:C52) -> 0 | D53: =SUM(D50:D52) -> 0 | E53: =SUM(E50:E52) -> 0 | F53: =SUM(F50:F52) -> 0 | G53: =SUM(G50:G52) -> 0 | H53: =SUM(H50:H52) -> 0 | I53: =SUM(I50:I52) -> 0 | ... N53: =SUM(N50:N52) -> 0 | O53: =SUM(C53:N53) -> 0
A55: Equipment Costs - Expenses (on Income Statement)
A56: Desktops | O56: =SUM(C56:N56) -> 0
A57: Monitors | O57: =SUM(C57:N57) -> 0
A58: Notebooks | O58: =SUM(C58:N58) -> 0
A59: Network Equipment | O59: =SUM(C59:N59) -> 0
A60: Equipment Maintenance | O60: =SUM(C60:N60) -> 0
A61: Other | O61: =SUM(C61:N61) -> 0
A62: Total Equipment Costs - Expenses | B62: =SUM(B56:B61) -> 0 | C62: =SUM(C56:C61) -> 0 | D62: =SUM(D56:D61) -> 0 | E62: =SUM(E56:E61) -> 0 | F62: =SUM(F56:F61) -> 0 | G62: =SUM(G56:G61) -> 0 | H62: =SUM(H56:H61) -> 0 | I62: =SUM(I56:I61) -> 0 | ... N62: =SUM(N56:N61) -> 0 | O62: =SUM(C62:N62) -> 0
A64: Equipment - Parts Expense
A65: Hard Drives | O65: =SUM(C65:N65) -> 0
A66: Mortherboards | O66: =SUM(C66:N66) -> 0
A67: CD Drives | O67: =SUM(C67:N67) -> 0
A68: Keyboards | O68: =SUM(C68:N68) -> 0
A69: Mice | O69: =SUM(C69:N69) -> 0
A70: Other | O70: =SUM(C70:N70) -> 0
A71: Total Equipment Costs - Parts Expense | B71: =SUM(B65:B70) -> 0 | C71: =SUM(C65:C70) -> 0 | D71: =SUM(D65:D70) -> 0 | E71: =SUM(E65:E70) -> 0 | F71: =SUM(F65:F70) -> 0 | G71: =SUM(G65:G70) -> 0 | H71: =SUM(H65:H70) -> 0 | I71: =SUM(I65:I70) -> 0 | ... N71: =SUM(N65:N70) -> 0 | O71: =SUM(C71:N71) -> 0
A73: Software Expenses
A74: Server Software | O74: =SUM(C74:N74) -> 0
A75: Microsoft Servers | O75: =SUM(C75:N75) -> 0
A76: Other Servers | O76: =SUM(C76:N76) -> 0
A77: Desktop Software | O77: =SUM(C77:N77) -> 0
A78: Microsoft Office | O78: =SUM(C78:N78) -> 0
A79: Other Desktop Software | O79: =SUM(C79:N79) -> 0
A80: Other Software | O80: =SUM(C80:N80) -> 0
A81: Total Software Expenses | B81: =SUM(B74:B80) -> 0 | C81: =SUM(C74:C80) -> 0 | D81: =SUM(D74:D80) -> 0 | E81: =SUM(E74:E80) -> 0 | F81: =SUM(F74:F80) -> 0 | G81: =SUM(G74:G80) -> 0 | H81: =SUM(H74:H80) -> 0 | I81: =SUM(I74:I80) -> 0 | ... N81: =SUM(N74:N80) -> 0 | O81: =SUM(C81:N81) -> 0
A83: General Administrative Overhead Expenses
A84: Payroll Expense | O84: =SUM(C84:N84) -> 0
A85: Legal Expenses | O85: =SUM(C85:N85) -> 0
A86: Utilities | O86: =SUM(C86:N86) -> 0
A87: Insurance | O87: =SUM(C87:N87) -> 0
A88: Rent | O88: =SUM(C88:N88) -> 0
A89: Other | O89: =SUM(C89:N89) -> 0
A90: Total General Administrative Overhead Expenses | B90: =SUM(B84:B89) -> 0 | C90: =SUM(C84:C89) -> 0 | D90: =SUM(D84:D89) -> 0 | E90: =SUM(E84:E89) -> 0 | F90: =SUM(F84:F89) -> 0 | G90: =SUM(G84:G89) -> 0 | H90: =SUM(H84:H89) -> 0 | I90: =SUM(I84:I89) -> 0 | ... N90: =SUM(N84:N89) -> 0 | O90: =SUM(C90:N90) -> 0
A92: TOTAL EXPENSES | B92: =+B30+B37+B47+B62+B71+B81+B90 -> 620000 | C92: =+C30+C37+C47+C62+C71+C81+C90 -> 21970 | D92: =+D30+D37+D47+D62+D71+D81+D90 -> 54370 | E92: =+E30+E37+E47+E62+E71+E81+E90 -> 64370 | F92: =+F30+F37+F47+F62+F71+F81+F90 -> 64370 | G92: =+G30+G37+G47+G62+G71+G81+G90 -> 64370 | H92: =+H30+H37+H47+H62+H71+H81+H90 -> 99786.667 | I92: =+I30+I37+I47+I62+I71+I81+I90 -> 99786.667 | ... N92: =+N30+N37+N47+N62+N71+N81+N90 -> 64370 | O92: =SUM(C92:N92) -> 932540
A94: TOTAL CAPITAL COSTS | B94: =+B53 -> 0 | C94: =+C53 -> 0 | D94: =+D53 -> 0 | E94: =+E53 -> 0 | F94: =+F53 -> 0 | G94: =+G53 -> 0 | H94: =+H53 -> 0 | I94: =+I53 -> 0 | ... N94: =+N53 -> 0 | O94: =SUM(C94:N94) -> 0
A96: TOTAL DEPARTMENT SPENDING | B96: =+B92+B94 -> 620000 | C96: =+C92+C94 -> 21970 | D96: =+D92+D94 -> 54370 | E96: =+E92+E94 -> 64370 | F96: =+F92+F94 -> 64370 | G96: =+G92+G94 -> 64370 | H96: =+H92+H94 -> 99786.667 | I96: =+I92+I94 -> 99786.667 | ... N96: =+N92+N94 -> 64370 | O96: =SUM(C96:N96) -> 932540
A98: TOTAL DEPARTMENT BUDGET (NET OF REVENUES) | B98: =B96-B7 -> 420000 | C98: =C96-C7 -> 21970 | D98: =D96-D7 -> 54370 | E98: =E96-E7 -> 64370 | F98: =F96-F7 -> 64370 | G98: =G96-G7 -> 64370 | H98: =H96-H7 -> 99786.667 | I98: =I96-I7 -> 99786.667 | ... N98: =N96-N7 -> 64370 | O98: =SUM(C98:N98) -> 932540

Sheet 3. Department Budget
A1: IT Department Budget | B1: Last Year's Budget | C1: This Year's Budget | D1: % of Total IT Spending | E1: % Change From Last Year | F1: Comments/Assumptions
A2: For Year Ending: | C2: (Total Year)
A3: DEPARTMENT REVENUES
A4: Fees IT Charges for Services Performed | B4: ='2. Monthly Worksheet'!B4 -> 180000 | C4: ='2. Monthly Worksheet'!O4 -> 198000 | D4: =IF(G4=0,G4,(C4/$C$95)) -> 0.21232333 | E4: =IF(H4=0,0,((C4-B4)/B4)) -> 0.1 | G4: =$C$95 -> 932540 | H4: =B4 -> 180000
A5: Proceeds from Sales of Assets | B5: ='2. Monthly Worksheet'!B5 -> 20000 | C5: ='2. Monthly Worksheet'!O5 -> 0 | D5: =IF(G5=0,G5,(C5/$C$95)) -> 0 | E5: =IF(H5=0,0,((C5-B5)/B5)) -> -1 | G5: =$C$95 -> 932540 | H5: =B5 -> 20000
A6: Other | B6: ='2. Monthly Worksheet'!B6 -> 0 | C6: ='2. Monthly Worksheet'!O6 -> 0 | D6: =IF(G6=0,G6,(C6/$C$95)) -> 0 | E6: =IF(H6=0,0,((C6-B6)/B6)) -> 0 | G6: =$C$95 -> 932540 | H6: =B6 -> 0
A7: Total Department Revenue | B7: =SUM(B4:B6) -> 200000 | C7: =SUM(C4:C6) -> 198000 | D7: =IF(G7=0,G7,(C7/$C$95)) -> 0.21232333 | E7: =IF(H7=0,0,((C7-B7)/B7)) -> -0.01 | G7: =$C$95 -> 932540 | H7: =B7 -> 200000
G8: =$C$95 -> 932540 | H8: =B8 -> 0
A9: PERSONNEL | G9: =$C$95 -> 932540 | H9: =B9 -> 0
A10: Headcount (People not Dollars) | G10: =$C$95 -> 932540 | H10: =B10 -> 0
A11: Full-Time | E11: =IF(H11=0,0,((C11-B11)/B11)) -> 0 | G11: =$C$95 -> 932540 | H11: =B11 -> 0
A12: Contract | E12: =IF(H12=0,0,((C12-B12)/B12)) -> 0 | G12: =$C$95 -> 932540 | H12: =B12 -> 0
A13: Other | E13: =IF(H13=0,0,((C13-B13)/B13)) -> 0 | G13: =$C$95 -> 932540 | H13: =B13 -> 0
A14: Total Headcount | B14: =SUM(B11:B13) -> 0 | C14: =SUM(C11:C13) -> 0 | E14: =IF(H14=0,0,((C14-B14)/B14)) -> 0 | G14: =$C$95 -> 932540 | H14: =B14 -> 0
A16: DEPARTMENT EXPENSES | G16: =$C$95 -> 932540 | H16: =B16 -> 0
A17: Personnel Expenses (Dollars not People) | G17: =$C$95 -> 932540 | H17: =B17 -> 0
A18: Full-Time Salaries | B18: ='2. Monthly Worksheet'!B18 -> 325000 | C18: ='2. Monthly Worksheet'!O18 -> 356400 | D18: =IF(G18=0,G18,(C18/$C$95)) -> 0.382182 | E18: =IF(H18=0,0,((C18-B18)/B18)) -> 0.096615385 | G18: =$C$95 -> 932540 | H18: =B18 -> 325000
A19: Temporary Workers | B19: ='2. Monthly Worksheet'!B19 -> 0 | C19: ='2. Monthly Worksheet'!O19 -> 0 | D19: =IF(G19=0,G19,(C19/$C$95)) -> 0 | E19: =IF(H19=0,0,((C19-B19)/B19)) -> 0 | G19: =$C$95 -> 932540 | H19: =B19 -> 0
A20: Bonuses / Other Compensation | B20: ='2. Monthly Worksheet'!B20 -> 40000 | C20: ='2. Monthly Worksheet'!O20 -> 0 | D20: =IF(G20=0,G20,(C20/$C$95)) -> 0 | E20: =IF(H20=0,0,((C20-B20)/B20)) -> -1 | G20: =$C$95 -> 932540 | H20: =B20 -> 40000
A21: Employee Benefits | B21: ='2. Monthly Worksheet'!B21 -> 0 | C21: ='2. Monthly Worksheet'!O21 -> 8640 | D21: =IF(G21=0,G21,(C21/$C$95)) -> 0.0092650181 | E21: =IF(H21=0,0,((C21-B21)/B21)) -> 0 | G21: =$C$95 -> 932540 | H21: =B21 -> 0
A22: Consultants | B22: ='2. Monthly Worksheet'!B22 -> 0 | C22: ='2. Monthly Worksheet'!O22 -> 100000 | D22: =IF(G22=0,G22,(C22/$C$95)) -> 0.10723401 | E22: =IF(H22=0,0,((C22-B22)/B22)) -> 0 | G22: =$C$95 -> 932540 | H22: =B22 -> 0
A23: Outsourcing Contracts | B23: ='2. Monthly Worksheet'!B23 -> 255000 | C23: ='2. Monthly Worksheet'!O23 -> 467500 | D23: =IF(G23=0,G23,(C23/$C$95)) -> 0.50131898 | E23: =IF(H23=0,0,((C23-B23)/B23)) -> 0.83333333 | G23: =$C$95 -> 932540 | H23: =B23 -> 255000
A24: Training / Seminars | B24: ='2. Monthly Worksheet'!B24 -> 0 | C24: ='2. Monthly Worksheet'!O24 -> 0 | D24: =IF(G24=0,G24,(C24/$C$95)) -> 0 | E24: =IF(H24=0,0,((C24-B24)/B24)) -> 0 | G24: =$C$95 -> 932540 | H24: =B24 -> 0
A25: Automobile Expense | B25: ='2. Monthly Worksheet'!B25 -> 0 | C25: ='2. Monthly Worksheet'!O25 -> 0 | D25: =IF(G25=0,G25,(C25/$C$95)) -> 0 | E25: =IF(H25=0,0,((C25-B25)/B25)) -> 0 | G25: =$C$95 -> 932540 | H25: =B25 -> 0
A26: Travel (e.g. Plane Tickets) | B26: ='2. Monthly Worksheet'!B26 -> 0 | C26: ='2. Monthly Worksheet'!O26 -> 0 | D26: =IF(G26=0,G26,(C26/$C$95)) -> 0 | E26: =IF(H26=0,0,((C26-B26)/B26)) -> 0 | G26: =$C$95 -> 932540 | H26: =B26 -> 0
A27: Accomodation (e.g. Hotels) | B27: ='2. Monthly Worksheet'!B27 -> 0 | C27: ='2. Monthly Worksheet'!O27 -> 0 | D27: =IF(G27=0,G27,(C27/$C$95)) -> 0 | E27: =IF(H27=0,0,((C27-B27)/B27)) -> 0 | G27: =$C$95 -> 932540 | H27: =B27 -> 0
A28: Meals | B28: ='2. Monthly Worksheet'!B28 -> 0 | C28: ='2. Monthly Worksheet'!O28 -> 0 | D28: =IF(G28=0,G28,(C28/$C$95)) -> 0 | E28: =IF(H28=0,0,((C28-B28)/B28)) -> 0 | G28: =$C$95 -> 932540 | H28: =B28 -> 0
A29: Employee Relocation | B29: ='2. Monthly Worksheet'!B29 -> 0 | C29: ='2. Monthly Worksheet'!O29 -> 0 | D29: =IF(G29=0,G29,(C29/$C$95)) -> 0 | E29: =IF(H29=0,0,((C29-B29)/B29)) -> 0 | G29: =$C$95 -> 932540 | H29: =B29 -> 0
A30: Total Personnel Expenses | B30: =SUM(B18:B29) -> 620000 | C30: =SUM(C18:C29) -> 932540 | D30: =IF(G30=0,G30,(C30/$C$95)) -> 1 | E30: =IF(H30=0,0,((C30-B30)/B30)) -> 0.50409677 | G30: =$C$95 -> 932540 | H30: =B30 -> 620000
G31: =$C$95 -> 932540 | H31: =B31 -> 0
A32: Office Supplies | G32: =$C$95 -> 932540 | H32: =B32 -> 0
A33: General Supplies | B33: ='2. Monthly Worksheet'!B33 -> 0 | C33: ='2. Monthly Worksheet'!O33 -> 0 | D33: =IF(G33=0,G33,(C33/$C$95)) -> 0 | E33: =IF(H33=0,0,((C33-B33)/B33)) -> 0 | G33: =$C$95 -> 932540 | H33: =B33 -> 0
A34: Media Costs (Diskettes, CDs, Tapes, etc.) | B34: ='2. Monthly Worksheet'!B34 -> 0 | C34: ='2. Monthly Worksheet'!O34 -> 0 | D34: =IF(G34=0,G34,(C34/$C$95)) -> 0 | E34: =IF(H34=0,0,((C34-B34)/B34)) -> 0 | G34: =$C$95 -> 932540 | H34: =B34 -> 0
A35: Postage / Freight | B35: ='2. Monthly Worksheet'!B35 -> 0 | C35: ='2. Monthly Worksheet'!O35 -> 0 | D35: =IF(G35=0,G35,(C35/$C$95)) -> 0 | E35: =IF(H35=0,0,((C35-B35)/B35)) -> 0 | G35: =$C$95 -> 932540 | H35: =B35 -> 0
A36: Publication Costs | B36: ='2. Monthly Worksheet'!B36 -> 0 | C36: ='2. Monthly Worksheet'!O36 -> 0 | D36: =IF(G36=0,G36,(C36/$C$95)) -> 0 | E36: =IF(H36=0,0,((C36-B36)/B36)) -> 0 | G36: =$C$95 -> 932540 | H36: =B36 -> 0
A37: Total Office Supplies | B37: =SUM(B33:B36) -> 0 | C37: =SUM(C33:C36) -> 0 | D37: =IF(G37=0,G37,(C37/$C$95)) -> 0 | E37: =IF(H37=0,0,((C37-B37)/B37)) -> 0 | G37: =$C$95 -> 932540 | H37: =B37 -> 0
G38: =$C$95 -> 932540 | H38: =B38 -> 0
A39: Telecommunications Expenses | G39: =$C$95 -> 932540 | H39: =B39 -> 0
A40: Local Telephone | B40: ='2. Monthly Worksheet'!B40 -> 0 | C40: ='2. Monthly Worksheet'!O40 -> 0 | D40: =IF(G40=0,G40,(C40/$C$95)) -> 0 | E40: =IF(H40=0,0,((C40-B40)/B40)) -> 0 | G40: =$C$95 -> 932540 | H40: =B40 -> 0
A41: Long Distance | B41: ='2. Monthly Worksheet'!B41 -> 0 | C41: ='2. Monthly Worksheet'!O41 -> 0 | D41: =IF(G41=0,G41,(C41/$C$95)) -> 0 | E41: =IF(H41=0,0,((C41-B41)/B41)) -> 0 | G41: =$C$95 -> 932540 | H41: =B41 -> 0
A42: Cellular | B42: ='2. Monthly Worksheet'!B42 -> 0 | C42: ='2. Monthly Worksheet'!O42 -> 0 | D42: =IF(G42=0,G42,(C42/$C$95)) -> 0 | E42: =IF(H42=0,0,((C42-B42)/B42)) -> 0 | G42: =$C$95 -> 932540 | H42: =B42 -> 0
A43: Pagers | B43: ='2. Monthly Worksheet'!B43 -> 0 | C43: ='2. Monthly Worksheet'!O43 -> 0 | D43: =IF(G43=0,G43,(C43/$C$95)) -> 0 | E43: =IF(H43=0,0,((C43-B43)/B43)) -> 0 | G43: =$C$95 -> 932540 | H43: =B43 -> 0
A44: Communications Lines | B44: ='2. Monthly Worksheet'!B44 -> 0 | C44: ='2. Monthly Worksheet'!O44 -> 0 | D44: =IF(G44=0,G44,(C44/$C$95)) -> 0 | E44: =IF(H44=0,0,((C44-B44)/B44)) -> 0 | G44: =$C$95 -> 932540 | H44: =B44 -> 0
A45: Internet Access | B45: ='2. Monthly Worksheet'!B45 -> 0 | C45: ='2. Monthly Worksheet'!O45 -> 0 | D45: =IF(G45=0,G45,(C45/$C$95)) -> 0 | E45: =IF(H45=0,0,((C45-B45)/B45)) -> 0 | G45: =$C$95 -> 932540 | H45: =B45 -> 0
A46: Other | B46: ='2. Monthly Worksheet'!B46 -> 0 | C46: ='2. Monthly Worksheet'!O46 -> 0 | D46: =IF(G46=0,G46,(C46/$C$95)) -> 0 | E46: =IF(H46=0,0,((C46-B46)/B46)) -> 0 | G46: =$C$95 -> 932540 | H46: =B46 -> 0
A47: Total Telecommunications Expenses | B47: =SUM(B40:B46) -> 0 | C47: =SUM(C40:C46) -> 0 | D47: =IF(G47=0,G47,(C47/$C$95)) -> 0 | E47: =IF(H47=0,0,((C47-B47)/B47)) -> 0 | G47: =$C$95 -> 932540 | H47: =B47 -> 0
G48: =$C$95 -> 932540 | H48: =B48 -> 0
A49: Equipment Costs - Capital (on Balance Sheet) | G49: =$C$95 -> 932540 | H49: =B49 -> 0
A50: Servers | B50: ='2. Monthly Worksheet'!B50 -> 0 | C50: ='2. Monthly Worksheet'!O50 -> 0 | D50: =IF(G50=0,G50,(C50/$C$95)) -> 0 | E50: =IF(H50=0,0,((C50-B50)/B50)) -> 0 | G50: =$C$95 -> 932540 | H50: =B50 -> 0
A51: Network Equipment | B51: ='2. Monthly Worksheet'!B51 -> 0 | C51: ='2. Monthly Worksheet'!O51 -> 0 | D51: =IF(G51=0,G51,(C51/$C$95)) -> 0 | E51: =IF(H51=0,0,((C51-B51)/B51)) -> 0 | G51: =$C$95 -> 932540 | H51: =B51 -> 0
A52: Other | B52: ='2. Monthly Worksheet'!B52 -> 0 | C52: ='2. Monthly Worksheet'!O52 -> 0 | D52: =IF(G52=0,G52,(C52/$C$95)) -> 0 | E52: =IF(H52=0,0,((C52-B52)/B52)) -> 0 | G52: =$C$95 -> 932540 | H52: =B52 -> 0
A53: Total Equipment Costs - Capital | B53: =SUM(B50:B52) -> 0 | C53: =SUM(C50:C52) -> 0 | D53: =IF(G53=0,G53,(C53/$C$95)) -> 0 | E53: =IF(H53=0,0,((C53-B53)/B53)) -> 0 | G53: =$C$95 -> 932540 | H53: =B53 -> 0
G54: =$C$95 -> 932540 | H54: =B54 -> 0
A55: Equipment Costs - Expenses (on Income Statement) | G55: =$C$95 -> 932540 | H55: =B55 -> 0
A56: Desktops | B56: ='2. Monthly Worksheet'!B56 -> 0 | C56: ='2. Monthly Worksheet'!O56 -> 0 | D56: =IF(G56=0,G56,(C56/$C$95)) -> 0 | E56: =IF(H56=0,0,((C56-B56)/B56)) -> 0 | G56: =$C$95 -> 932540 | H56: =B56 -> 0
A57: Monitors | B57: ='2. Monthly Worksheet'!B57 -> 0 | C57: ='2. Monthly Worksheet'!O57 -> 0 | D57: =IF(G57=0,G57,(C57/$C$95)) -> 0 | E57: =IF(H57=0,0,((C57-B57)/B57)) -> 0 | G57: =$C$95 -> 932540 | H57: =B57 -> 0
A58: Notebooks | B58: ='2. Monthly Worksheet'!B58 -> 0 | C58: ='2. Monthly Worksheet'!O58 -> 0 | D58: =IF(G58=0,G58,(C58/$C$95)) -> 0 | E58: =IF(H58=0,0,((C58-B58)/B58)) -> 0 | G58: =$C$95 -> 932540 | H58: =B58 -> 0
A59: Network Equipment | B59: ='2. Monthly Worksheet'!B59 -> 0 | C59: ='2. Monthly Worksheet'!O59 -> 0 | D59: =IF(G59=0,G59,(C59/$C$95)) -> 0 | E59: =IF(H59=0,0,((C59-B59)/B59)) -> 0 | G59: =$C$95 -> 932540 | H59: =B59 -> 0
A60: Equipment Maintenance | B60: ='2. Monthly Worksheet'!B60 -> 0 | C60: ='2. Monthly Worksheet'!O60 -> 0 | D60: =IF(G60=0,G60,(C60/$C$95)) -> 0 | E60: =IF(H60=0,0,((C60-B60)/B60)) -> 0 | G60: =$C$95 -> 932540 | H60: =B60 -> 0
A61: Other | B61: ='2. Monthly Worksheet'!B61 -> 0 | C61: ='2. Monthly Worksheet'!O61 -> 0 | D61: =IF(G61=0,G61,(C61/$C$95)) -> 0 | E61: =IF(H61=0,0,((C61-B61)/B61)) -> 0 | G61: =$C$95 -> 932540 | H61: =B61 -> 0
A62: Total Equipment Costs - Expenses | B62: =SUM(B56:B61) -> 0 | C62: =SUM(C56:C61) -> 0 | D62: =IF(G62=0,G62,(C62/$C$95)) -> 0 | E62: =IF(H62=0,0,((C62-B62)/B62)) -> 0 | G62: =$C$95 -> 932540 | H62: =B62 -> 0
G63: =$C$95 -> 932540 | H63: =B63 -> 0
A64: Equipment - Parts Expense | G64: =$C$95 -> 932540 | H64: =B64 -> 0
A65: Hard Drives | B65: ='2. Monthly Worksheet'!B65 -> 0 | C65: ='2. Monthly Worksheet'!O65 -> 0 | D65: =IF(G65=0,G65,(C65/$C$95)) -> 0 | E65: =IF(H65=0,0,((C65-B65)/B65)) -> 0 | G65: =$C$95 -> 932540 | H65: =B65 -> 0
A66: Mortherboards | B66: ='2. Monthly Worksheet'!B66 -> 0 | C66: ='2. Monthly Worksheet'!O66 -> 0 | D66: =IF(G66=0,G66,(C66/$C$95)) -> 0 | E66: =IF(H66=0,0,((C66-B66)/B66)) -> 0 | G66: =$C$95 -> 932540 | H66: =B66 -> 0
A67: CD Drives | B67: ='2. Monthly Worksheet'!B67 -> 0 | C67: ='2. Monthly Worksheet'!O67 -> 0 | D67: =IF(G67=0,G67,(C67/$C$95)) -> 0 | E67: =IF(H67=0,0,((C67-B67)/B67)) -> 0 | G67: =$C$95 -> 932540 | H67: =B67 -> 0
A68: Keyboards | B68: ='2. Monthly Worksheet'!B68 -> 0 | C68: ='2. Monthly Worksheet'!O68 -> 0 | D68: =IF(G68=0,G68,(C68/$C$95)) -> 0 | E68: =IF(H68=0,0,((C68-B68)/B68)) -> 0 | G68: =$C$95 -> 932540 | H68: =B68 -> 0
A69: Mice | B69: ='2. Monthly Worksheet'!B69 -> 0 | C69: ='2. Monthly Worksheet'!O69 -> 0 | D69: =IF(G69=0,G69,(C69/$C$95)) -> 0 | E69: =IF(H69=0,0,((C69-B69)/B69)) -> 0 | G69: =$C$95 -> 932540 | H69: =B69 -> 0
A70: Other | B70: ='2. Monthly Worksheet'!B70 -> 0 | C70: ='2. Monthly Worksheet'!O70 -> 0 | D70: =IF(G70=0,G70,(C70/$C$95)) -> 0 | E70: =IF(H70=0,0,((C70-B70)/B70)) -> 0 | G70: =$C$95 -> 932540 | H70: =B70 -> 0
A71: Total Equipment Costs - Parts Expense | B71: =SUM(B65:B70) -> 0 | C71: =SUM(C65:C70) -> 0 | D71: =IF(G71=0,G71,(C71/$C$95)) -> 0 | E71: =IF(H71=0,0,((C71-B71)/B71)) -> 0 | G71: =$C$95 -> 932540 | H71: =B71 -> 0
G72: =$C$95 -> 932540 | H72: =B72 -> 0
A73: Software Expenses | G73: =$C$95 -> 932540 | H73: =B73 -> 0
A74: Server Software | B74: ='2. Monthly Worksheet'!B74 -> 0 | C74: ='2. Monthly Worksheet'!O74 -> 0 | D74: =IF(G74=0,G74,(C74/$C$95)) -> 0 | E74: =IF(H74=0,0,((C74-B74)/B74)) -> 0 | G74: =$C$95 -> 932540 | H74: =B74 -> 0
A75: Microsoft Servers | B75: ='2. Monthly Worksheet'!B75 -> 0 | C75: ='2. Monthly Worksheet'!O75 -> 0 | D75: =IF(G75=0,G75,(C75/$C$95)) -> 0 | E75: =IF(H75=0,0,((C75-B75)/B75)) -> 0 | G75: =$C$95 -> 932540 | H75: =B75 -> 0
A76: Other Servers | B76: ='2. Monthly Worksheet'!B76 -> 0 | C76: ='2. Monthly Worksheet'!O76 -> 0 | D76: =IF(G76=0,G76,(C76/$C$95)) -> 0 | E76: =IF(H76=0,0,((C76-B76)/B76)) -> 0 | G76: =$C$95 -> 932540 | H76: =B76 -> 0
A77: Desktop Software | B77: ='2. Monthly Worksheet'!B77 -> 0 | C77: ='2. Monthly Worksheet'!O77 -> 0 | D77: =IF(G77=0,G77,(C77/$C$95)) -> 0 | E77: =IF(H77=0,0,((C77-B77)/B77)) -> 0 | G77: =$C$95 -> 932540 | H77: =B77 -> 0
A78: Microsoft Office | B78: ='2. Monthly Worksheet'!B78 -> 0 | C78: ='2. Monthly Worksheet'!O78 -> 0 | D78: =IF(G78=0,G78,(C78/$C$95)) -> 0 | E78: =IF(H78=0,0,((C78-B78)/B78)) -> 0 | G78: =$C$95 -> 932540 | H78: =B78 -> 0
A79: Other Desktop Software | B79: ='2. Monthly Worksheet'!B79 -> 0 | C79: ='2. Monthly Worksheet'!O79 -> 0 | D79: =IF(G79=0,G79,(C79/$C$95)) -> 0 | E79: =IF(H79=0,0,((C79-B79)/B79)) -> 0 | G79: =$C$95 -> 932540 | H79: =B79 -> 0
A80: Other Software | B80: ='2. Monthly Worksheet'!B80 -> 0 | C80: ='2. Monthly Worksheet'!O80 -> 0 | D80: =IF(G80=0,G80,(C80/$C$95)) -> 0 | E80: =IF(H80=0,0,((C80-B80)/B80)) -> 0 | G80: =$C$95 -> 932540 | H80: =B80 -> 0
A81: Total Software Expenses | B81: =SUM(B74:B80) -> 0 | C81: =SUM(C74:C80) -> 0 | D81: =IF(G81=0,G81,(C81/$C$95)) -> 0 | E81: =IF(H81=0,0,((C81-B81)/B81)) -> 0 | G81: =$C$95 -> 932540 | H81: =B81 -> 0
G82: =$C$95 -> 932540 | H82: =B82 -> 0
A83: General Administrative Overhead Expenses | G83: =$C$95 -> 932540 | H83: =B83 -> 0
A84: Payroll Expense | B84: ='2. Monthly Worksheet'!B84 -> 0 | C84: ='2. Monthly Worksheet'!O84 -> 0 | D84: =IF(G84=0,G84,(C84/$C$95)) -> 0 | E84: =IF(H84=0,0,((C84-B84)/B84)) -> 0 | G84: =$C$95 -> 932540 | H84: =B84 -> 0
A85: Legal Expenses | B85: ='2. Monthly Worksheet'!B85 -> 0 | C85: ='2. Monthly Worksheet'!O85 -> 0 | D85: =IF(G85=0,G85,(C85/$C$95)) -> 0 | E85: =IF(H85=0,0,((C85-B85)/B85)) -> 0 | G85: =$C$95 -> 932540 | H85: =B85 -> 0
A86: Utilities | B86: ='2. Monthly Worksheet'!B86 -> 0 | C86: ='2. Monthly Worksheet'!O86 -> 0 | D86: =IF(G86=0,G86,(C86/$C$95)) -> 0 | E86: =IF(H86=0,0,((C86-B86)/B86)) -> 0 | G86: =$C$95 -> 932540 | H86: =B86 -> 0
A87: Insurance | B87: ='2. Monthly Worksheet'!B87 -> 0 | C87: ='2. Monthly Worksheet'!O87 -> 0 | D87: =IF(G87=0,G87,(C87/$C$95)) -> 0 | E87: =IF(H87=0,0,((C87-B87)/B87)) -> 0 | G87: =$C$95 -> 932540 | H87: =B87 -> 0
A88: Rent | B88: ='2. Monthly Worksheet'!B88 -> 0 | C88: ='2. Monthly Worksheet'!O88 -> 0 | D88: =IF(G88=0,G88,(C88/$C$95)) -> 0 | E88: =IF(H88=0,0,((C88-B88)/B88)) -> 0 | G88: =$C$95 -> 932540 | H88: =B88 -> 0
A89: Other | B89: ='2. Monthly Worksheet'!B89 -> 0 | C89: ='2. Monthly Worksheet'!O89 -> 0 | D89: =IF(G89=0,G89,(C89/$C$95)) -> 0 | E89: =IF(H89=0,0,((C89-B89)/B89)) -> 0 | G89: =$C$95 -> 932540 | H89: =B89 -> 0
A90: Total General Administrative Overhead Expenses | B90: =SUM(B84:B89) -> 0 | C90: =SUM(C84:C89) -> 0 | D90: =IF(G90=0,G90,(C90/$C$95)) -> 0 | E90: =IF(H90=0,0,((C90-B90)/B90)) -> 0 | G90: =$C$95 -> 932540 | H90: =B90 -> 0
G91: =$C$95 -> 932540 | H91: =B91 -> 0
A92: TOTAL EXPENSES | B92: =+B30+B37+B47+B62+B71+B81+B90 -> 620000 | C92: =+C30+C37+C47+C62+C71+C81+C90 -> 932540 | D92: =IF(G92=0,G92,(C92/$C$95)) -> 1 | E92: =IF(H92=0,0,((C92-B92)/B92)) -> 0.50409677 | G92: =$C$95 -> 932540 | H92: =B92 -> 620000
A93: TOTAL CAPITAL COSTS | B93: =+B53 -> 0 | C93: =+C53 -> 0 | D93: =IF(G93=0,G93,(C93/$C$95)) -> 0 | E93: =IF(H93=0,0,((C93-B93)/B93)) -> 0 | G93: =$C$95 -> 932540 | H93: =B93 -> 0
G94: =$C$95 -> 932540 | H94: =B94 -> 0
A95: TOTAL DEPARTMENT SPENDING | B95: =+B92+B93 -> 620000 | C95: =+C92+C93 -> 932540 | D95: =IF(G95=0,G95,(C95/$C$95)) -> 1 | E95: =IF(H95=0,0,((C95-B95)/B95)) -> 0.50409677 | G95: =$C$95 -> 932540 | H95: =B95 -> 620000
G96: =$C$95 -> 932540 | H96: =B96 -> 0
A97: TOTAL DEPARTMENT BUDGET (NET OF REVENUES) | B97: =B95-B7 -> 420000 | C97: =C95-C7 -> 734540 | D97: =IF(G97=0,G97,(C97/$C$95)) -> 0.78767667 | E97: =IF(H97=0,0,((C97-B97)/B97)) -> 0.74890476 | G97: =$C$95 -> 932540 | H97: =B97 -> 420000
